{"chunk_definitions":[{"row":118,"row_count":1,"visible":true,"expansion_state":0,"options":{"engine":"r","label":"unnamed-chunk-121","dev":"png"},"document_id":"BADBABA6","chunk_id":"c3mdz8sd18ih8","chunk_label":"unnamed-chunk-1"},{"row":161,"row_count":1,"visible":true,"expansion_state":0,"options":{"engine":"r","label":"unnamed-chunk-122","echo":false,"dev":"png"},"document_id":"D704AA7D","chunk_id":"cchnufey9un31","chunk_label":"unnamed-chunk-3"},{"row":192,"row_count":1,"visible":true,"expansion_state":0,"options":{"engine":"r","label":"unnamed-chunk-123","eval":true,"dev":"png"},"document_id":"24D721B4","chunk_id":"cwc94821siu41","chunk_label":"unnamed-chunk-4"},{"row":212,"row_count":1,"visible":true,"expansion_state":0,"options":{"engine":"r","label":"setup","include":false,"dev":"png"},"document_id":"964FD138","chunk_id":"csetup_chunk","chunk_label":"setup"},{"row":290,"row_count":1,"visible":true,"expansion_state":0,"options":{"engine":"r","label":"unnamed-chunk-124","dev":"png"},"document_id":"964FD138","chunk_id":"cfosk1jxbblr2","chunk_label":"unnamed-chunk-5"},{"row":323,"row_count":1,"visible":true,"expansion_state":0,"options":{"engine":"r","label":"unnamed-chunk-125","dev":"png"},"document_id":"964FD138","chunk_id":"c3dw405crcrqu","chunk_label":"unnamed-chunk-6"},{"row":356,"row_count":1,"visible":true,"expansion_state":0,"options":{"engine":"r","label":"unnamed-chunk-126","dev":"png"},"document_id":"964FD138","chunk_id":"c2plgpbgsdtt0","chunk_label":"unnamed-chunk-7"},{"row":379,"row_count":1,"visible":true,"expansion_state":0,"options":{"engine":"r","label":"unnamed-chunk-127","dev":"png"},"document_id":"964FD138","chunk_id":"cxtz1o83kfkqp","chunk_label":"unnamed-chunk-8"},{"row":431,"row_count":1,"visible":true,"expansion_state":0,"options":{"engine":"r","label":"unnamed-chunk-128","dev":"png"},"document_id":"964FD138","chunk_id":"c3bywbhlb56c3","chunk_label":"unnamed-chunk-9"},{"row":468,"row_count":1,"visible":true,"expansion_state":0,"options":{"engine":"r","label":"unnamed-chunk-129","dev":"png"},"document_id":"964FD138","chunk_id":"chmixrhi49sem","chunk_label":"unnamed-chunk-10"},{"row":502,"row_count":1,"visible":true,"expansion_state":0,"options":{"engine":"r","label":"unnamed-chunk-130","dev":"png"},"document_id":"964FD138","chunk_id":"c6nyeb98bl2be","chunk_label":"unnamed-chunk-11"},{"row":532,"row_count":1,"visible":true,"expansion_state":0,"options":{"engine":"r","label":"unnamed-chunk-131","dev":"png"},"document_id":"964FD138","chunk_id":"c0cnddc0dound","chunk_label":"unnamed-chunk-12"},{"row":565,"row_count":1,"visible":true,"expansion_state":0,"options":{"engine":"r","label":"unnamed-chunk-132","dev":"png"},"document_id":"964FD138","chunk_id":"cy5z9ax7r8ybq","chunk_label":"unnamed-chunk-13"},{"row":590,"row_count":1,"visible":true,"expansion_state":0,"options":{"engine":"r","label":"unnamed-chunk-133","dev":"png"},"document_id":"964FD138","chunk_id":"ccw9exgte6k0z","chunk_label":"unnamed-chunk-14"},{"row":626,"row_count":1,"visible":true,"expansion_state":0,"options":{"engine":"r","label":"unnamed-chunk-134","dev":"png"},"document_id":"964FD138","chunk_id":"c25er505lec2i","chunk_label":"unnamed-chunk-15"}],"doc_write_time":1767405528,"chunk_rendered_width":700,"working_dir":null,"default_chunk_options":{}}